vulp/__init__.py
vulp/spine/__init__.py
vulp/spine/exceptions.py
vulp/spine/request.py
vulp/spine/spine_interface.py
vulp/utils/__init__.py
vulp/utils/serialize.py
vulp-2.5.1.dist-info/LICENSE
vulp-2.5.1.dist-info/WHEEL
vulp-2.5.1.dist-info/METADATA
vulp-2.5.1.dist-info/RECORD
