Metadata-Version: 2.1
Name: vulp
Version: 2.5.1
Summary: Robot/simulation switch for the mjbots stack.
Keywords: motion control,real time,robotics
Author-email: Stéphane Caron <stephane.caron@normalesup.org>
Maintainer-email: Stéphane Caron <stephane.caron@normalesup.org>
Requires-Python: >=3.7
Classifier: Development Status :: 7 - Inactive
Classifier: Framework :: Robot Framework :: Library
Classifier: Intended Audience :: Developers
Classifier: Intended Audience :: Science/Research
Classifier: License :: OSI Approved :: Apache Software License
Classifier: Operating System :: OS Independent
Classifier: Programming Language :: Python :: 3.8
Classifier: Programming Language :: Python :: 3.9
Classifier: Programming Language :: Python :: 3.10
Classifier: Programming Language :: Python :: 3.11
Classifier: Topic :: Scientific/Engineering
Requires-Dist: msgpack >=1.0.2
Project-URL: Changelog, https://github.com/upkie/vulp/blob/main/CHANGELOG.md
Project-URL: Documentation, https://upkie.github.io/vulp/
Project-URL: Source, https://github.com/upkie/vulp
